modeltee.py
modeltee-0.1.1.dist-info/LICENSE
modeltee-0.1.1.dist-info/WHEEL
modeltee-0.1.1.dist-info/METADATA
modeltee-0.1.1.dist-info/RECORD
