Metadata-Version: 1.2
Name: modeltee
Version: 0.1.1
Summary: A framework for automating software releases
Home-page: https://gitlab.com/takluyver/modeltee
License: UNKNOWN
Author: Thomas Kluyver
Author-email: thomas@kluyver.me.uk
Requires-Python: >=3.6
Classifier: Intended Audience :: Developers
Classifier: License :: OSI Approved :: BSD License
Classifier: Programming Language :: Python :: 3
